saf_datasets/__init__.py
saf_datasets/annotators/__init__.py
saf_datasets/annotators/allennlp_srl.py
saf_datasets/annotators/amr.py
saf_datasets/annotators/models.py
saf_datasets/annotators/spacy.py
saf_datasets/annotators/transformer.py
saf_datasets/data_access/__init__.py
saf_datasets/data_access/allnli.py
saf_datasets/data_access/codwoe.py
saf_datasets/data_access/complex_sentences.py
saf_datasets/data_access/cpae.py
saf_datasets/data_access/dataset.py
saf_datasets/data_access/entailmentbank.py
saf_datasets/data_access/inference_types.py
saf_datasets/data_access/snli.py
saf_datasets/data_access/stsb.py
saf_datasets/data_access/wiktionary.py
saf_datasets/data_access/wordnet_filtered.py
saf_datasets/data_access/wordnet_spanish.py
saf_datasets/data_access/yahoo.py
saf_datasets/data_access/yelp_st.py
saf_datasets/wrappers/__init__.py
saf_datasets/wrappers/hf.py
saf_datasets/wrappers/torch.py
saf_datasets-0.6.18.dist-info/licenses/LICENSE
saf_datasets-0.6.18.dist-info/METADATA
saf_datasets-0.6.18.dist-info/WHEEL
saf_datasets-0.6.18.dist-info/top_level.txt
saf_datasets-0.6.18.dist-info/RECORD
