Metadata-Version: 2.4
Name: saf-datasets
Version: 0.6.18
Summary: Data set loading and annotation facilities for the Simple Annotation Framework
Home-page: 
Author: Danilo S. Carvalho
Author-email: "Danilo S. Carvalho" <danilo.carvalho@manchester.ac.uk>
Project-URL: Homepage, https://github.com/neuro-symbolic-ai/saf_datasets
Project-URL: Issues, https://github.com/neuro-symbolic-ai/saf_datasets/issues
Keywords: datasets,annotated,nlp
Classifier: Programming Language :: Python :: 3
Classifier: Operating System :: OS Independent
Requires-Python: >=3.9
License-File: LICENSE
Requires-Dist: saf-nlp
Requires-Dist: spacy
Requires-Dist: gdown
Requires-Dist: tqdm
Requires-Dist: torch
Requires-Dist: jsonlines
Requires-Dist: transformers
Requires-Dist: sentencepiece
Requires-Dist: protobuf
Dynamic: author
Dynamic: license-file
